[
  {
    "ContainingType": "WebApplicationtest.Controllers.ChiTietHoaDonBanController",
    "Method": "CreateItem",
    "RelativePath": "api/ChiTietHoaDonBan/create-item",
    "HttpMethod": "POST",
    "IsController": true,
    "Order": 0,
    "Parameters": [
      {
        "Name": "model",
        "Type": "Model.ChiTietHoaDonBanModel",
        "IsRequired": true
      }
    ],
    "ReturnTypes": [
      {
        "Type": "Model.ChiTietHoaDonBanModel",
        "MediaTypes": [
          "text/plain",
          "application/json",
          "text/json"
        ],
        "StatusCode": 200
      }
    ]
  },
  {
    "ContainingType": "WebApplicationtest.Controllers.ChiTietHoaDonBanController",
    "Method": "DeleteItem",
    "RelativePath": "api/ChiTietHoaDonBan/delete-item",
    "HttpMethod": "DELETE",
    "IsController": true,
    "Order": 0,
    "Parameters": [
      {
        "Name": "id",
        "Type": "System.String",
        "IsRequired": true
      }
    ],
    "ReturnTypes": []
  },
  {
    "ContainingType": "WebApplicationtest.Controllers.ChiTietHoaDonBanController",
    "Method": "GetAllItem",
    "RelativePath": "api/ChiTietHoaDonBan/getall-item",
    "HttpMethod": "GET",
    "IsController": true,
    "Order": 0,
    "Parameters": [],
    "ReturnTypes": [
      {
        "Type": "System.Collections.Generic.IEnumerable\u00601[[Model.ChiTietHoaDonBanModel, Model, Version=1.0.0.0, Culture=neutral, PublicKeyToken=null]]",
        "MediaTypes": [
          "text/plain",
          "application/json",
          "text/json"
        ],
        "StatusCode": 200
      }
    ]
  },
  {
    "ContainingType": "WebApplicationtest.Controllers.ChiTietHoaDonBanController",
    "Method": "GetAllItembyID",
    "RelativePath": "api/ChiTietHoaDonBan/getall-itembyid",
    "HttpMethod": "GET",
    "IsController": true,
    "Order": 0,
    "Parameters": [
      {
        "Name": "id",
        "Type": "System.Int32",
        "IsRequired": false
      }
    ],
    "ReturnTypes": [
      {
        "Type": "System.Collections.Generic.IEnumerable\u00601[[Model.ChiTietHoaDonBanModel, Model, Version=1.0.0.0, Culture=neutral, PublicKeyToken=null]]",
        "MediaTypes": [
          "text/plain",
          "application/json",
          "text/json"
        ],
        "StatusCode": 200
      }
    ]
  },
  {
    "ContainingType": "WebApplicationtest.Controllers.ChiTietHoaDonBanController",
    "Method": "GetAllItembyIDtheoMaHD",
    "RelativePath": "api/ChiTietHoaDonBan/getall-itembyidmahd",
    "HttpMethod": "GET",
    "IsController": true,
    "Order": 0,
    "Parameters": [
      {
        "Name": "id",
        "Type": "System.Int32",
        "IsRequired": false
      }
    ],
    "ReturnTypes": [
      {
        "Type": "System.Collections.Generic.IEnumerable\u00601[[Model.CHiTietHDBanKHModel, Model, Version=1.0.0.0, Culture=neutral, PublicKeyToken=null]]",
        "MediaTypes": [
          "text/plain",
          "application/json",
          "text/json"
        ],
        "StatusCode": 200
      }
    ]
  },
  {
    "ContainingType": "WebApplicationtest.Controllers.ChiTietHoaDonBanController",
    "Method": "ThemHoaDon",
    "RelativePath": "api/ChiTietHoaDonBan/ThemHoaDon",
    "HttpMethod": "POST",
    "IsController": true,
    "Order": 0,
    "Parameters": [
      {
        "Name": "model",
        "Type": "System.Collections.Generic.List\u00601[[Model.ThongTinHoaDonMoDel, Model, Version=1.0.0.0, Culture=neutral, PublicKeyToken=null]]",
        "IsRequired": true
      }
    ],
    "ReturnTypes": []
  },
  {
    "ContainingType": "WebApplicationtest.Controllers.ChiTietHoaDonBanController",
    "Method": "UpdateItem",
    "RelativePath": "api/ChiTietHoaDonBan/update-item",
    "HttpMethod": "PUT",
    "IsController": true,
    "Order": 0,
    "Parameters": [
      {
        "Name": "model",
        "Type": "Model.ChiTietHoaDonBanModel",
        "IsRequired": true
      }
    ],
    "ReturnTypes": [
      {
        "Type": "Model.ChiTietHoaDonBanModel",
        "MediaTypes": [
          "text/plain",
          "application/json",
          "text/json"
        ],
        "StatusCode": 200
      }
    ]
  },
  {
    "ContainingType": "WebApplicationtest.Controllers.ChiTietHoaDonNhapADMINController",
    "Method": "CreateItem",
    "RelativePath": "api/ChiTietHoaDonNhapADMIN/create-item",
    "HttpMethod": "POST",
    "IsController": true,
    "Order": 0,
    "Parameters": [
      {
        "Name": "model",
        "Type": "Model.HoaDonNhapADMINModel",
        "IsRequired": true
      }
    ],
    "ReturnTypes": [
      {
        "Type": "Model.HoaDonNhapADMINModel",
        "MediaTypes": [
          "text/plain",
          "application/json",
          "text/json"
        ],
        "StatusCode": 200
      }
    ]
  },
  {
    "ContainingType": "WebApplicationtest.Controllers.ChiTietHoaDonNhapADMINController",
    "Method": "DeleteItem",
    "RelativePath": "api/ChiTietHoaDonNhapADMIN/delete-item",
    "HttpMethod": "DELETE",
    "IsController": true,
    "Order": 0,
    "Parameters": [
      {
        "Name": "id",
        "Type": "System.String",
        "IsRequired": true
      }
    ],
    "ReturnTypes": []
  },
  {
    "ContainingType": "WebApplicationtest.Controllers.ChiTietHoaDonNhapADMINController",
    "Method": "GetAllItem",
    "RelativePath": "api/ChiTietHoaDonNhapADMIN/getall-item",
    "HttpMethod": "GET",
    "IsController": true,
    "Order": 0,
    "Parameters": [],
    "ReturnTypes": [
      {
        "Type": "System.Collections.Generic.IEnumerable\u00601[[Model.HoaDonNhapADMINModel, Model, Version=1.0.0.0, Culture=neutral, PublicKeyToken=null]]",
        "MediaTypes": [
          "text/plain",
          "application/json",
          "text/json"
        ],
        "StatusCode": 200
      }
    ]
  },
  {
    "ContainingType": "WebApplicationtest.Controllers.ChiTietHoaDonNhapADMINController",
    "Method": "GetAllItembyID",
    "RelativePath": "api/ChiTietHoaDonNhapADMIN/getall-itembyid",
    "HttpMethod": "GET",
    "IsController": true,
    "Order": 0,
    "Parameters": [
      {
        "Name": "id",
        "Type": "System.Int32",
        "IsRequired": false
      }
    ],
    "ReturnTypes": [
      {
        "Type": "System.Collections.Generic.IEnumerable\u00601[[Model.HoaDonNhapADMINModel, Model, Version=1.0.0.0, Culture=neutral, PublicKeyToken=null]]",
        "MediaTypes": [
          "text/plain",
          "application/json",
          "text/json"
        ],
        "StatusCode": 200
      }
    ]
  },
  {
    "ContainingType": "WebApplicationtest.Controllers.ChiTietHoaDonNhapADMINController",
    "Method": "GetAllItemDT",
    "RelativePath": "api/ChiTietHoaDonNhapADMIN/getall-itemdt",
    "HttpMethod": "GET",
    "IsController": true,
    "Order": 0,
    "Parameters": [],
    "ReturnTypes": [
      {
        "Type": "System.Collections.Generic.IEnumerable\u00601[[Model.ThongKeDoanhThu, Model, Version=1.0.0.0, Culture=neutral, PublicKeyToken=null]]",
        "MediaTypes": [
          "text/plain",
          "application/json",
          "text/json"
        ],
        "StatusCode": 200
      }
    ]
  },
  {
    "ContainingType": "WebApplicationtest.Controllers.ChiTietHoaDonNhapADMINController",
    "Method": "UpdateItem",
    "RelativePath": "api/ChiTietHoaDonNhapADMIN/update-item",
    "HttpMethod": "PUT",
    "IsController": true,
    "Order": 0,
    "Parameters": [
      {
        "Name": "model",
        "Type": "Model.HoaDonNhapADMINModel",
        "IsRequired": true
      }
    ],
    "ReturnTypes": [
      {
        "Type": "Model.HoaDonNhapADMINModel",
        "MediaTypes": [
          "text/plain",
          "application/json",
          "text/json"
        ],
        "StatusCode": 200
      }
    ]
  },
  {
    "ContainingType": "WebApplicationtest.Controllers.ChiTietSanPhamController",
    "Method": "CreateItem",
    "RelativePath": "api/ChiTietSanPham/create-item",
    "HttpMethod": "POST",
    "IsController": true,
    "Order": 0,
    "Parameters": [
      {
        "Name": "model",
        "Type": "Model.ChiTietSanPhamModel",
        "IsRequired": true
      }
    ],
    "ReturnTypes": [
      {
        "Type": "Model.ChiTietSanPhamModel",
        "MediaTypes": [
          "text/plain",
          "application/json",
          "text/json"
        ],
        "StatusCode": 200
      }
    ]
  },
  {
    "ContainingType": "WebApplicationtest.Controllers.ChiTietSanPhamController",
    "Method": "DeleteItem",
    "RelativePath": "api/ChiTietSanPham/delete-item",
    "HttpMethod": "DELETE",
    "IsController": true,
    "Order": 0,
    "Parameters": [
      {
        "Name": "id",
        "Type": "System.String",
        "IsRequired": true
      }
    ],
    "ReturnTypes": []
  },
  {
    "ContainingType": "WebApplicationtest.Controllers.ChiTietSanPhamController",
    "Method": "GetAllItembyID",
    "RelativePath": "api/ChiTietSanPham/getall-itembyid",
    "HttpMethod": "GET",
    "IsController": true,
    "Order": 0,
    "Parameters": [
      {
        "Name": "id",
        "Type": "System.Int32",
        "IsRequired": false
      }
    ],
    "ReturnTypes": [
      {
        "Type": "System.Collections.Generic.IEnumerable\u00601[[Model.ChiTietSanPhamModel1, Model, Version=1.0.0.0, Culture=neutral, PublicKeyToken=null]]",
        "MediaTypes": [
          "text/plain",
          "application/json",
          "text/json"
        ],
        "StatusCode": 200
      }
    ]
  },
  {
    "ContainingType": "WebApplicationtest.Controllers.ChiTietSanPhamController",
    "Method": "UpdateItem",
    "RelativePath": "api/ChiTietSanPham/update-item",
    "HttpMethod": "PUT",
    "IsController": true,
    "Order": 0,
    "Parameters": [
      {
        "Name": "model",
        "Type": "Model.ChiTietSanPhamModel",
        "IsRequired": true
      }
    ],
    "ReturnTypes": [
      {
        "Type": "Model.ChiTietSanPhamModel",
        "MediaTypes": [
          "text/plain",
          "application/json",
          "text/json"
        ],
        "StatusCode": 200
      }
    ]
  },
  {
    "ContainingType": "WebApplicationtest.Controllers.DanhMucController",
    "Method": "CreateItem",
    "RelativePath": "api/DanhMuc/create-item",
    "HttpMethod": "POST",
    "IsController": true,
    "Order": 0,
    "Parameters": [
      {
        "Name": "model",
        "Type": "Model.DanhMucModel",
        "IsRequired": true
      }
    ],
    "ReturnTypes": [
      {
        "Type": "Model.DanhMucModel",
        "MediaTypes": [
          "text/plain",
          "application/json",
          "text/json"
        ],
        "StatusCode": 200
      }
    ]
  },
  {
    "ContainingType": "WebApplicationtest.Controllers.DanhMucController",
    "Method": "DeleteItem",
    "RelativePath": "api/DanhMuc/delete-item",
    "HttpMethod": "DELETE",
    "IsController": true,
    "Order": 0,
    "Parameters": [
      {
        "Name": "model",
        "Type": "Model.DanhMucModel",
        "IsRequired": true
      }
    ],
    "ReturnTypes": [
      {
        "Type": "Model.DanhMucModel",
        "MediaTypes": [
          "text/plain",
          "application/json",
          "text/json"
        ],
        "StatusCode": 200
      }
    ]
  },
  {
    "ContainingType": "WebApplicationtest.Controllers.DanhMucController",
    "Method": "GetAllItem",
    "RelativePath": "api/DanhMuc/getall-item",
    "HttpMethod": "GET",
    "IsController": true,
    "Order": 0,
    "Parameters": [],
    "ReturnTypes": [
      {
        "Type": "System.Collections.Generic.IEnumerable\u00601[[Model.DanhMucModel, Model, Version=1.0.0.0, Culture=neutral, PublicKeyToken=null]]",
        "MediaTypes": [
          "text/plain",
          "application/json",
          "text/json"
        ],
        "StatusCode": 200
      }
    ]
  },
  {
    "ContainingType": "WebApplicationtest.Controllers.DanhMucController",
    "Method": "UpdateItem",
    "RelativePath": "api/DanhMuc/update-item",
    "HttpMethod": "PUT",
    "IsController": true,
    "Order": 0,
    "Parameters": [
      {
        "Name": "model",
        "Type": "Model.DanhMucModel",
        "IsRequired": true
      }
    ],
    "ReturnTypes": [
      {
        "Type": "Model.DanhMucModel",
        "MediaTypes": [
          "text/plain",
          "application/json",
          "text/json"
        ],
        "StatusCode": 200
      }
    ]
  },
  {
    "ContainingType": "WebApplicationtest.Controllers.DNController",
    "Method": "CreateItem",
    "RelativePath": "api/DN/create-item",
    "HttpMethod": "POST",
    "IsController": true,
    "Order": 0,
    "Parameters": [
      {
        "Name": "model",
        "Type": "Model.DangNhapModel",
        "IsRequired": true
      }
    ],
    "ReturnTypes": [
      {
        "Type": "Model.DangNhapModel",
        "MediaTypes": [
          "text/plain",
          "application/json",
          "text/json"
        ],
        "StatusCode": 200
      }
    ]
  },
  {
    "ContainingType": "WebApplicationtest.Controllers.DNController",
    "Method": "DeleteItem",
    "RelativePath": "api/DN/delete-item",
    "HttpMethod": "DELETE",
    "IsController": true,
    "Order": 0,
    "Parameters": [
      {
        "Name": "id",
        "Type": "System.String",
        "IsRequired": true
      }
    ],
    "ReturnTypes": []
  },
  {
    "ContainingType": "WebApplicationtest.Controllers.DNController",
    "Method": "GetAllItem",
    "RelativePath": "api/DN/getall-item",
    "HttpMethod": "GET",
    "IsController": true,
    "Order": 0,
    "Parameters": [],
    "ReturnTypes": [
      {
        "Type": "System.Collections.Generic.IEnumerable\u00601[[Model.DangNhapModel, Model, Version=1.0.0.0, Culture=neutral, PublicKeyToken=null]]",
        "MediaTypes": [
          "text/plain",
          "application/json",
          "text/json"
        ],
        "StatusCode": 200
      }
    ]
  },
  {
    "ContainingType": "WebApplicationtest.Controllers.DNController",
    "Method": "GetAllItembyID",
    "RelativePath": "api/DN/getall-itembyid",
    "HttpMethod": "GET",
    "IsController": true,
    "Order": 0,
    "Parameters": [
      {
        "Name": "id",
        "Type": "System.Int32",
        "IsRequired": false
      }
    ],
    "ReturnTypes": [
      {
        "Type": "System.Collections.Generic.IEnumerable\u00601[[Model.DangNhapModel, Model, Version=1.0.0.0, Culture=neutral, PublicKeyToken=null]]",
        "MediaTypes": [
          "text/plain",
          "application/json",
          "text/json"
        ],
        "StatusCode": 200
      }
    ]
  },
  {
    "ContainingType": "WebApplicationtest.Controllers.DNController",
    "Method": "GetAlltopItem",
    "RelativePath": "api/DN/getalltop-item",
    "HttpMethod": "GET",
    "IsController": true,
    "Order": 0,
    "Parameters": [],
    "ReturnTypes": [
      {
        "Type": "System.Collections.Generic.IEnumerable\u00601[[Model.DangNhapModel, Model, Version=1.0.0.0, Culture=neutral, PublicKeyToken=null]]",
        "MediaTypes": [
          "text/plain",
          "application/json",
          "text/json"
        ],
        "StatusCode": 200
      }
    ]
  },
  {
    "ContainingType": "WebApplicationtest.Controllers.DNController",
    "Method": "UpdateItem",
    "RelativePath": "api/DN/update-item",
    "HttpMethod": "PUT",
    "IsController": true,
    "Order": 0,
    "Parameters": [
      {
        "Name": "model",
        "Type": "Model.DangNhapModel",
        "IsRequired": true
      }
    ],
    "ReturnTypes": [
      {
        "Type": "Model.DangNhapModel",
        "MediaTypes": [
          "text/plain",
          "application/json",
          "text/json"
        ],
        "StatusCode": 200
      }
    ]
  },
  {
    "ContainingType": "WebApplicationtest.Controllers.GiaNhapController",
    "Method": "CreateItem",
    "RelativePath": "api/GiaNhap/create-item",
    "HttpMethod": "POST",
    "IsController": true,
    "Order": 0,
    "Parameters": [
      {
        "Name": "model",
        "Type": "Model.GiaNhapModel",
        "IsRequired": true
      }
    ],
    "ReturnTypes": [
      {
        "Type": "Model.GiaNhapModel",
        "MediaTypes": [
          "text/plain",
          "application/json",
          "text/json"
        ],
        "StatusCode": 200
      }
    ]
  },
  {
    "ContainingType": "WebApplicationtest.Controllers.GiaNhapController",
    "Method": "DeleteItem",
    "RelativePath": "api/GiaNhap/delete-item",
    "HttpMethod": "DELETE",
    "IsController": true,
    "Order": 0,
    "Parameters": [
      {
        "Name": "id",
        "Type": "System.String",
        "IsRequired": true
      }
    ],
    "ReturnTypes": []
  },
  {
    "ContainingType": "WebApplicationtest.Controllers.GiaNhapController",
    "Method": "GetAllItem",
    "RelativePath": "api/GiaNhap/getall-item",
    "HttpMethod": "GET",
    "IsController": true,
    "Order": 0,
    "Parameters": [],
    "ReturnTypes": [
      {
        "Type": "System.Collections.Generic.IEnumerable\u00601[[Model.GiaNhapModel, Model, Version=1.0.0.0, Culture=neutral, PublicKeyToken=null]]",
        "MediaTypes": [
          "text/plain",
          "application/json",
          "text/json"
        ],
        "StatusCode": 200
      }
    ]
  },
  {
    "ContainingType": "WebApplicationtest.Controllers.GiaNhapController",
    "Method": "GetAllItembyID",
    "RelativePath": "api/GiaNhap/getall-itembyid",
    "HttpMethod": "GET",
    "IsController": true,
    "Order": 0,
    "Parameters": [
      {
        "Name": "id",
        "Type": "System.Int32",
        "IsRequired": false
      }
    ],
    "ReturnTypes": [
      {
        "Type": "System.Collections.Generic.IEnumerable\u00601[[Model.GiaNhapModel, Model, Version=1.0.0.0, Culture=neutral, PublicKeyToken=null]]",
        "MediaTypes": [
          "text/plain",
          "application/json",
          "text/json"
        ],
        "StatusCode": 200
      }
    ]
  },
  {
    "ContainingType": "WebApplicationtest.Controllers.GiaNhapController",
    "Method": "GetAllItembyID",
    "RelativePath": "api/GiaNhap/getalltop-item",
    "HttpMethod": "GET",
    "IsController": true,
    "Order": 0,
    "Parameters": [
      {
        "Name": "id",
        "Type": "System.Int32",
        "IsRequired": false
      }
    ],
    "ReturnTypes": [
      {
        "Type": "System.Collections.Generic.IEnumerable\u00601[[Model.GiaNhapModel, Model, Version=1.0.0.0, Culture=neutral, PublicKeyToken=null]]",
        "MediaTypes": [
          "text/plain",
          "application/json",
          "text/json"
        ],
        "StatusCode": 200
      }
    ]
  },
  {
    "ContainingType": "WebApplicationtest.Controllers.GiaNhapController",
    "Method": "UpdateItem",
    "RelativePath": "api/GiaNhap/update-item",
    "HttpMethod": "PUT",
    "IsController": true,
    "Order": 0,
    "Parameters": [
      {
        "Name": "model",
        "Type": "Model.GiaNhapModel",
        "IsRequired": true
      }
    ],
    "ReturnTypes": [
      {
        "Type": "Model.GiaNhapModel",
        "MediaTypes": [
          "text/plain",
          "application/json",
          "text/json"
        ],
        "StatusCode": 200
      }
    ]
  },
  {
    "ContainingType": "WebApplicationtest.Controllers.GioHangController",
    "Method": "CreateItem",
    "RelativePath": "api/GioHang/create-item",
    "HttpMethod": "POST",
    "IsController": true,
    "Order": 0,
    "Parameters": [
      {
        "Name": "model",
        "Type": "Model.GioHangModel",
        "IsRequired": true
      }
    ],
    "ReturnTypes": [
      {
        "Type": "Model.GioHangModel",
        "MediaTypes": [
          "text/plain",
          "application/json",
          "text/json"
        ],
        "StatusCode": 200
      }
    ]
  },
  {
    "ContainingType": "WebApplicationtest.Controllers.GioHangController",
    "Method": "DeleteItem",
    "RelativePath": "api/GioHang/delete-item",
    "HttpMethod": "DELETE",
    "IsController": true,
    "Order": 0,
    "Parameters": [
      {
        "Name": "id",
        "Type": "System.String",
        "IsRequired": false
      },
      {
        "Name": "UserID",
        "Type": "System.String",
        "IsRequired": false
      }
    ],
    "ReturnTypes": []
  },
  {
    "ContainingType": "WebApplicationtest.Controllers.GioHangController",
    "Method": "GetAllItem",
    "RelativePath": "api/GioHang/getall-item",
    "HttpMethod": "GET",
    "IsController": true,
    "Order": 0,
    "Parameters": [],
    "ReturnTypes": [
      {
        "Type": "System.Collections.Generic.IEnumerable\u00601[[Model.GioHangModel, Model, Version=1.0.0.0, Culture=neutral, PublicKeyToken=null]]",
        "MediaTypes": [
          "text/plain",
          "application/json",
          "text/json"
        ],
        "StatusCode": 200
      }
    ]
  },
  {
    "ContainingType": "WebApplicationtest.Controllers.GioHangController",
    "Method": "GetAllItembyID",
    "RelativePath": "api/GioHang/getall-itembyid",
    "HttpMethod": "GET",
    "IsController": true,
    "Order": 0,
    "Parameters": [
      {
        "Name": "id",
        "Type": "System.String",
        "IsRequired": false
      }
    ],
    "ReturnTypes": [
      {
        "Type": "System.Collections.Generic.IEnumerable\u00601[[Model.GioHangKH1, Model, Version=1.0.0.0, Culture=neutral, PublicKeyToken=null]]",
        "MediaTypes": [
          "text/plain",
          "application/json",
          "text/json"
        ],
        "StatusCode": 200
      }
    ]
  },
  {
    "ContainingType": "WebApplicationtest.Controllers.GioHangController",
    "Method": "GetAllItembyIDGiamGH",
    "RelativePath": "api/GioHang/getall-itembyidGiamGH",
    "HttpMethod": "GET",
    "IsController": true,
    "Order": 0,
    "Parameters": [
      {
        "Name": "id",
        "Type": "System.String",
        "IsRequired": false
      },
      {
        "Name": "UserID",
        "Type": "System.String",
        "IsRequired": false
      }
    ],
    "ReturnTypes": [
      {
        "Type": "System.Collections.Generic.IEnumerable\u00601[[Model.GioHangKH1, Model, Version=1.0.0.0, Culture=neutral, PublicKeyToken=null]]",
        "MediaTypes": [
          "text/plain",
          "application/json",
          "text/json"
        ],
        "StatusCode": 200
      }
    ]
  },
  {
    "ContainingType": "WebApplicationtest.Controllers.GioHangController",
    "Method": "GetAllItembyIDTangGH",
    "RelativePath": "api/GioHang/getall-itembyidTangGH",
    "HttpMethod": "GET",
    "IsController": true,
    "Order": 0,
    "Parameters": [
      {
        "Name": "id",
        "Type": "System.String",
        "IsRequired": false
      },
      {
        "Name": "UserID",
        "Type": "System.String",
        "IsRequired": false
      }
    ],
    "ReturnTypes": [
      {
        "Type": "System.Collections.Generic.IEnumerable\u00601[[Model.GioHangKH1, Model, Version=1.0.0.0, Culture=neutral, PublicKeyToken=null]]",
        "MediaTypes": [
          "text/plain",
          "application/json",
          "text/json"
        ],
        "StatusCode": 200
      }
    ]
  },
  {
    "ContainingType": "WebApplicationtest.Controllers.GioHangController",
    "Method": "GetAllItembyIDThemGH",
    "RelativePath": "api/GioHang/getall-itembyidThemGH",
    "HttpMethod": "GET",
    "IsController": true,
    "Order": 0,
    "Parameters": [
      {
        "Name": "id",
        "Type": "System.String",
        "IsRequired": false
      },
      {
        "Name": "UserID",
        "Type": "System.String",
        "IsRequired": false
      }
    ],
    "ReturnTypes": [
      {
        "Type": "System.Collections.Generic.IEnumerable\u00601[[Model.GioHangKH1, Model, Version=1.0.0.0, Culture=neutral, PublicKeyToken=null]]",
        "MediaTypes": [
          "text/plain",
          "application/json",
          "text/json"
        ],
        "StatusCode": 200
      }
    ]
  },
  {
    "ContainingType": "WebApplicationtest.Controllers.GioHangController",
    "Method": "GetAlltopItem",
    "RelativePath": "api/GioHang/getalltop-item",
    "HttpMethod": "GET",
    "IsController": true,
    "Order": 0,
    "Parameters": [],
    "ReturnTypes": [
      {
        "Type": "System.Collections.Generic.IEnumerable\u00601[[Model.GioHangModel, Model, Version=1.0.0.0, Culture=neutral, PublicKeyToken=null]]",
        "MediaTypes": [
          "text/plain",
          "application/json",
          "text/json"
        ],
        "StatusCode": 200
      }
    ]
  },
  {
    "ContainingType": "WebApplicationtest.Controllers.GioHangController",
    "Method": "UpdateItem",
    "RelativePath": "api/GioHang/update-item",
    "HttpMethod": "PUT",
    "IsController": true,
    "Order": 0,
    "Parameters": [
      {
        "Name": "model",
        "Type": "Model.GioHangModel",
        "IsRequired": true
      }
    ],
    "ReturnTypes": [
      {
        "Type": "Model.GioHangModel",
        "MediaTypes": [
          "text/plain",
          "application/json",
          "text/json"
        ],
        "StatusCode": 200
      }
    ]
  },
  {
    "ContainingType": "WebApplicationtest.Controllers.HoaDonBanController",
    "Method": "CreateItem",
    "RelativePath": "api/HoaDonBan/create-item",
    "HttpMethod": "POST",
    "IsController": true,
    "Order": 0,
    "Parameters": [
      {
        "Name": "model",
        "Type": "Model.HoaDonBanModel",
        "IsRequired": true
      }
    ],
    "ReturnTypes": [
      {
        "Type": "Model.HoaDonBanModel",
        "MediaTypes": [
          "text/plain",
          "application/json",
          "text/json"
        ],
        "StatusCode": 200
      }
    ]
  },
  {
    "ContainingType": "WebApplicationtest.Controllers.HoaDonBanController",
    "Method": "DeleteItem",
    "RelativePath": "api/HoaDonBan/delete-item",
    "HttpMethod": "DELETE",
    "IsController": true,
    "Order": 0,
    "Parameters": [
      {
        "Name": "id",
        "Type": "System.String",
        "IsRequired": true
      }
    ],
    "ReturnTypes": []
  },
  {
    "ContainingType": "WebApplicationtest.Controllers.HoaDonBanController",
    "Method": "GetAllItem",
    "RelativePath": "api/HoaDonBan/getall-item",
    "HttpMethod": "GET",
    "IsController": true,
    "Order": 0,
    "Parameters": [],
    "ReturnTypes": [
      {
        "Type": "System.Collections.Generic.IEnumerable\u00601[[Model.HoaDonBanModel, Model, Version=1.0.0.0, Culture=neutral, PublicKeyToken=null]]",
        "MediaTypes": [
          "text/plain",
          "application/json",
          "text/json"
        ],
        "StatusCode": 200
      }
    ]
  },
  {
    "ContainingType": "WebApplicationtest.Controllers.HoaDonBanController",
    "Method": "GetAllItembyID",
    "RelativePath": "api/HoaDonBan/getall-itembyid",
    "HttpMethod": "GET",
    "IsController": true,
    "Order": 0,
    "Parameters": [
      {
        "Name": "id",
        "Type": "System.Int32",
        "IsRequired": false
      }
    ],
    "ReturnTypes": [
      {
        "Type": "System.Collections.Generic.IEnumerable\u00601[[Model.HoaDonBanModel, Model, Version=1.0.0.0, Culture=neutral, PublicKeyToken=null]]",
        "MediaTypes": [
          "text/plain",
          "application/json",
          "text/json"
        ],
        "StatusCode": 200
      }
    ]
  },
  {
    "ContainingType": "WebApplicationtest.Controllers.HoaDonBanController",
    "Method": "GetAllItembyIDtheouser",
    "RelativePath": "api/HoaDonBan/getall-itembyidtheouser",
    "HttpMethod": "GET",
    "IsController": true,
    "Order": 0,
    "Parameters": [
      {
        "Name": "id",
        "Type": "System.String",
        "IsRequired": false
      }
    ],
    "ReturnTypes": [
      {
        "Type": "System.Collections.Generic.IEnumerable\u00601[[Model.HoaDonDatHangModel, Model, Version=1.0.0.0, Culture=neutral, PublicKeyToken=null]]",
        "MediaTypes": [
          "text/plain",
          "application/json",
          "text/json"
        ],
        "StatusCode": 200
      }
    ]
  },
  {
    "ContainingType": "WebApplicationtest.Controllers.HoaDonBanController",
    "Method": "GetAllItemTT",
    "RelativePath": "api/HoaDonBan/getall-itemTT",
    "HttpMethod": "GET",
    "IsController": true,
    "Order": 0,
    "Parameters": [],
    "ReturnTypes": [
      {
        "Type": "System.Collections.Generic.IEnumerable\u00601[[Model.HoaDonBanTTModel, Model, Version=1.0.0.0, Culture=neutral, PublicKeyToken=null]]",
        "MediaTypes": [
          "text/plain",
          "application/json",
          "text/json"
        ],
        "StatusCode": 200
      }
    ]
  },
  {
    "ContainingType": "WebApplicationtest.Controllers.HoaDonBanController",
    "Method": "GetAllHDMax",
    "RelativePath": "api/HoaDonBan/gettopmax",
    "HttpMethod": "GET",
    "IsController": true,
    "Order": 0,
    "Parameters": [],
    "ReturnTypes": [
      {
        "Type": "System.Collections.Generic.IEnumerable\u00601[[Model.HoaDonKhachHangModel, Model, Version=1.0.0.0, Culture=neutral, PublicKeyToken=null]]",
        "MediaTypes": [
          "text/plain",
          "application/json",
          "text/json"
        ],
        "StatusCode": 200
      }
    ]
  },
  {
    "ContainingType": "WebApplicationtest.Controllers.HoaDonBanController",
    "Method": "UpdateItem",
    "RelativePath": "api/HoaDonBan/update-item",
    "HttpMethod": "PUT",
    "IsController": true,
    "Order": 0,
    "Parameters": [
      {
        "Name": "model",
        "Type": "Model.HoaDonBanModel",
        "IsRequired": true
      }
    ],
    "ReturnTypes": [
      {
        "Type": "Model.HoaDonBanModel",
        "MediaTypes": [
          "text/plain",
          "application/json",
          "text/json"
        ],
        "StatusCode": 200
      }
    ]
  },
  {
    "ContainingType": "WebApplicationtest.Controllers.KhachHangController",
    "Method": "CreateItem",
    "RelativePath": "api/KhachHang/create-item",
    "HttpMethod": "POST",
    "IsController": true,
    "Order": 0,
    "Parameters": [
      {
        "Name": "model",
        "Type": "Model.KhachHangModel",
        "IsRequired": true
      }
    ],
    "ReturnTypes": [
      {
        "Type": "Model.KhachHangModel",
        "MediaTypes": [
          "text/plain",
          "application/json",
          "text/json"
        ],
        "StatusCode": 200
      }
    ]
  },
  {
    "ContainingType": "WebApplicationtest.Controllers.KhachHangController",
    "Method": "DeleteItem",
    "RelativePath": "api/KhachHang/delete-item",
    "HttpMethod": "DELETE",
    "IsController": true,
    "Order": 0,
    "Parameters": [
      {
        "Name": "id",
        "Type": "System.String",
        "IsRequired": true
      }
    ],
    "ReturnTypes": []
  },
  {
    "ContainingType": "WebApplicationtest.Controllers.KhachHangController",
    "Method": "GetAllItem",
    "RelativePath": "api/KhachHang/getall-item",
    "HttpMethod": "GET",
    "IsController": true,
    "Order": 0,
    "Parameters": [],
    "ReturnTypes": [
      {
        "Type": "System.Collections.Generic.IEnumerable\u00601[[Model.KhachHangModel, Model, Version=1.0.0.0, Culture=neutral, PublicKeyToken=null]]",
        "MediaTypes": [
          "text/plain",
          "application/json",
          "text/json"
        ],
        "StatusCode": 200
      }
    ]
  },
  {
    "ContainingType": "WebApplicationtest.Controllers.KhachHangController",
    "Method": "GetAllItembyID",
    "RelativePath": "api/KhachHang/getall-itembyid",
    "HttpMethod": "GET",
    "IsController": true,
    "Order": 0,
    "Parameters": [
      {
        "Name": "id",
        "Type": "System.Int32",
        "IsRequired": false
      }
    ],
    "ReturnTypes": [
      {
        "Type": "System.Collections.Generic.IEnumerable\u00601[[Model.KhachHangModel, Model, Version=1.0.0.0, Culture=neutral, PublicKeyToken=null]]",
        "MediaTypes": [
          "text/plain",
          "application/json",
          "text/json"
        ],
        "StatusCode": 200
      }
    ]
  },
  {
    "ContainingType": "WebApplicationtest.Controllers.KhachHangController",
    "Method": "GetAllByIDtheoUser",
    "RelativePath": "api/KhachHang/getall-itembyiduser",
    "HttpMethod": "GET",
    "IsController": true,
    "Order": 0,
    "Parameters": [
      {
        "Name": "id",
        "Type": "System.String",
        "IsRequired": false
      }
    ],
    "ReturnTypes": [
      {
        "Type": "System.Collections.Generic.IEnumerable\u00601[[Model.KhachHangModel, Model, Version=1.0.0.0, Culture=neutral, PublicKeyToken=null]]",
        "MediaTypes": [
          "text/plain",
          "application/json",
          "text/json"
        ],
        "StatusCode": 200
      }
    ]
  },
  {
    "ContainingType": "WebApplicationtest.Controllers.KhachHangController",
    "Method": "UpdateItem",
    "RelativePath": "api/KhachHang/update-item",
    "HttpMethod": "PUT",
    "IsController": true,
    "Order": 0,
    "Parameters": [
      {
        "Name": "model",
        "Type": "Model.KhachHangModel",
        "IsRequired": true
      }
    ],
    "ReturnTypes": [
      {
        "Type": "Model.KhachHangModel",
        "MediaTypes": [
          "text/plain",
          "application/json",
          "text/json"
        ],
        "StatusCode": 200
      }
    ]
  },
  {
    "ContainingType": "WebApplicationtest.Controllers.KhachHangController",
    "Method": "UpdateItemtheouser",
    "RelativePath": "api/KhachHang/update-itemtheouser",
    "HttpMethod": "PUT",
    "IsController": true,
    "Order": 0,
    "Parameters": [
      {
        "Name": "model",
        "Type": "Model.KhachHangModel2",
        "IsRequired": true
      }
    ],
    "ReturnTypes": [
      {
        "Type": "Model.KhachHangModel2",
        "MediaTypes": [
          "text/plain",
          "application/json",
          "text/json"
        ],
        "StatusCode": 200
      }
    ]
  },
  {
    "ContainingType": "WebApplicationtest.Controllers.LoginController",
    "Method": "loginKH",
    "RelativePath": "api/Login/login-KH",
    "HttpMethod": "POST",
    "IsController": true,
    "Order": 0,
    "Parameters": [
      {
        "Name": "model",
        "Type": "Model.LoginModel",
        "IsRequired": true
      }
    ],
    "ReturnTypes": []
  },
  {
    "ContainingType": "WebApplicationtest.Controllers.NhaCUngCapController",
    "Method": "CreateItem",
    "RelativePath": "api/NhaCUngCap/create-item",
    "HttpMethod": "POST",
    "IsController": true,
    "Order": 0,
    "Parameters": [
      {
        "Name": "model",
        "Type": "Model.NhaCungCapModel",
        "IsRequired": true
      }
    ],
    "ReturnTypes": [
      {
        "Type": "Model.NhaCungCapModel",
        "MediaTypes": [
          "text/plain",
          "application/json",
          "text/json"
        ],
        "StatusCode": 200
      }
    ]
  },
  {
    "ContainingType": "WebApplicationtest.Controllers.NhaCUngCapController",
    "Method": "DeleteItem",
    "RelativePath": "api/NhaCUngCap/delete-item",
    "HttpMethod": "DELETE",
    "IsController": true,
    "Order": 0,
    "Parameters": [
      {
        "Name": "id",
        "Type": "System.String",
        "IsRequired": true
      }
    ],
    "ReturnTypes": []
  },
  {
    "ContainingType": "WebApplicationtest.Controllers.NhaCUngCapController",
    "Method": "GetAllItem",
    "RelativePath": "api/NhaCUngCap/getall-item",
    "HttpMethod": "GET",
    "IsController": true,
    "Order": 0,
    "Parameters": [],
    "ReturnTypes": [
      {
        "Type": "System.Collections.Generic.IEnumerable\u00601[[Model.NhaCungCapModel, Model, Version=1.0.0.0, Culture=neutral, PublicKeyToken=null]]",
        "MediaTypes": [
          "text/plain",
          "application/json",
          "text/json"
        ],
        "StatusCode": 200
      }
    ]
  },
  {
    "ContainingType": "WebApplicationtest.Controllers.NhaCUngCapController",
    "Method": "GetAllItembyID",
    "RelativePath": "api/NhaCUngCap/getall-itembyid",
    "HttpMethod": "GET",
    "IsController": true,
    "Order": 0,
    "Parameters": [
      {
        "Name": "id",
        "Type": "System.Int32",
        "IsRequired": false
      }
    ],
    "ReturnTypes": [
      {
        "Type": "System.Collections.Generic.IEnumerable\u00601[[Model.NhaCungCapModel, Model, Version=1.0.0.0, Culture=neutral, PublicKeyToken=null]]",
        "MediaTypes": [
          "text/plain",
          "application/json",
          "text/json"
        ],
        "StatusCode": 200
      }
    ]
  },
  {
    "ContainingType": "WebApplicationtest.Controllers.NhaCUngCapController",
    "Method": "GetAllByTenM",
    "RelativePath": "api/NhaCUngCap/getall-itembyidTenSP",
    "HttpMethod": "GET",
    "IsController": true,
    "Order": 0,
    "Parameters": [
      {
        "Name": "id",
        "Type": "System.String",
        "IsRequired": false
      }
    ],
    "ReturnTypes": [
      {
        "Type": "System.Collections.Generic.IEnumerable\u00601[[Model.NhaCungCapModel, Model, Version=1.0.0.0, Culture=neutral, PublicKeyToken=null]]",
        "MediaTypes": [
          "text/plain",
          "application/json",
          "text/json"
        ],
        "StatusCode": 200
      }
    ]
  },
  {
    "ContainingType": "WebApplicationtest.Controllers.NhaCUngCapController",
    "Method": "UpdateItem",
    "RelativePath": "api/NhaCUngCap/update-item",
    "HttpMethod": "PUT",
    "IsController": true,
    "Order": 0,
    "Parameters": [
      {
        "Name": "model",
        "Type": "Model.NhaCungCapModel",
        "IsRequired": true
      }
    ],
    "ReturnTypes": [
      {
        "Type": "Model.NhaCungCapModel",
        "MediaTypes": [
          "text/plain",
          "application/json",
          "text/json"
        ],
        "StatusCode": 200
      }
    ]
  },
  {
    "ContainingType": "WebApplicationtest.Controllers.SanPhamController",
    "Method": "CreateItem",
    "RelativePath": "api/SanPham/create-item",
    "HttpMethod": "POST",
    "IsController": true,
    "Order": 0,
    "Parameters": [
      {
        "Name": "model",
        "Type": "Model.SanPhamModel",
        "IsRequired": true
      }
    ],
    "ReturnTypes": [
      {
        "Type": "Model.SanPhamModel",
        "MediaTypes": [
          "text/plain",
          "application/json",
          "text/json"
        ],
        "StatusCode": 200
      }
    ]
  },
  {
    "ContainingType": "WebApplicationtest.Controllers.SanPhamController",
    "Method": "DeleteItem",
    "RelativePath": "api/SanPham/delete-item",
    "HttpMethod": "DELETE",
    "IsController": true,
    "Order": 0,
    "Parameters": [
      {
        "Name": "id",
        "Type": "System.String",
        "IsRequired": true
      }
    ],
    "ReturnTypes": []
  },
  {
    "ContainingType": "WebApplicationtest.Controllers.SanPhamController",
    "Method": "GetAllItem",
    "RelativePath": "api/SanPham/getall-item",
    "HttpMethod": "GET",
    "IsController": true,
    "Order": 0,
    "Parameters": [],
    "ReturnTypes": [
      {
        "Type": "System.Collections.Generic.IEnumerable\u00601[[Model.SanPhamModel, Model, Version=1.0.0.0, Culture=neutral, PublicKeyToken=null]]",
        "MediaTypes": [
          "text/plain",
          "application/json",
          "text/json"
        ],
        "StatusCode": 200
      }
    ]
  },
  {
    "ContainingType": "WebApplicationtest.Controllers.SanPhamController",
    "Method": "GetAllItemADMIN",
    "RelativePath": "api/SanPham/getall-itemadmin",
    "HttpMethod": "GET",
    "IsController": true,
    "Order": 0,
    "Parameters": [],
    "ReturnTypes": [
      {
        "Type": "System.Collections.Generic.IEnumerable\u00601[[Model.SanPhamADMINModel, Model, Version=1.0.0.0, Culture=neutral, PublicKeyToken=null]]",
        "MediaTypes": [
          "text/plain",
          "application/json",
          "text/json"
        ],
        "StatusCode": 200
      }
    ]
  },
  {
    "ContainingType": "WebApplicationtest.Controllers.SanPhamController",
    "Method": "GetAllItemADMINHetHang",
    "RelativePath": "api/SanPham/getall-itemadminhethang",
    "HttpMethod": "GET",
    "IsController": true,
    "Order": 0,
    "Parameters": [],
    "ReturnTypes": [
      {
        "Type": "System.Collections.Generic.IEnumerable\u00601[[Model.SanPhamADMINModel, Model, Version=1.0.0.0, Culture=neutral, PublicKeyToken=null]]",
        "MediaTypes": [
          "text/plain",
          "application/json",
          "text/json"
        ],
        "StatusCode": 200
      }
    ]
  },
  {
    "ContainingType": "WebApplicationtest.Controllers.SanPhamController",
    "Method": "GetAllItembyID",
    "RelativePath": "api/SanPham/getall-itembyid",
    "HttpMethod": "GET",
    "IsController": true,
    "Order": 0,
    "Parameters": [
      {
        "Name": "id",
        "Type": "System.Int32",
        "IsRequired": false
      }
    ],
    "ReturnTypes": [
      {
        "Type": "System.Collections.Generic.IEnumerable\u00601[[Model.SanPhamModel, Model, Version=1.0.0.0, Culture=neutral, PublicKeyToken=null]]",
        "MediaTypes": [
          "text/plain",
          "application/json",
          "text/json"
        ],
        "StatusCode": 200
      }
    ]
  },
  {
    "ContainingType": "WebApplicationtest.Controllers.SanPhamController",
    "Method": "GetAllItembyIDDM",
    "RelativePath": "api/SanPham/getall-itembyidDM",
    "HttpMethod": "GET",
    "IsController": true,
    "Order": 0,
    "Parameters": [
      {
        "Name": "id",
        "Type": "System.Int32",
        "IsRequired": false
      }
    ],
    "ReturnTypes": [
      {
        "Type": "System.Collections.Generic.IEnumerable\u00601[[Model.SanPhamModel, Model, Version=1.0.0.0, Culture=neutral, PublicKeyToken=null]]",
        "MediaTypes": [
          "text/plain",
          "application/json",
          "text/json"
        ],
        "StatusCode": 200
      }
    ]
  },
  {
    "ContainingType": "WebApplicationtest.Controllers.SanPhamController",
    "Method": "GetAllByTenM",
    "RelativePath": "api/SanPham/getall-itembyidTenSP",
    "HttpMethod": "GET",
    "IsController": true,
    "Order": 0,
    "Parameters": [
      {
        "Name": "id",
        "Type": "System.String",
        "IsRequired": false
      }
    ],
    "ReturnTypes": [
      {
        "Type": "System.Collections.Generic.IEnumerable\u00601[[Model.SanPhamModel, Model, Version=1.0.0.0, Culture=neutral, PublicKeyToken=null]]",
        "MediaTypes": [
          "text/plain",
          "application/json",
          "text/json"
        ],
        "StatusCode": 200
      }
    ]
  },
  {
    "ContainingType": "WebApplicationtest.Controllers.SanPhamController",
    "Method": "GetAlltopItem",
    "RelativePath": "api/SanPham/getalltop-item",
    "HttpMethod": "GET",
    "IsController": true,
    "Order": 0,
    "Parameters": [],
    "ReturnTypes": [
      {
        "Type": "System.Collections.Generic.IEnumerable\u00601[[Model.SanPhamModel, Model, Version=1.0.0.0, Culture=neutral, PublicKeyToken=null]]",
        "MediaTypes": [
          "text/plain",
          "application/json",
          "text/json"
        ],
        "StatusCode": 200
      }
    ]
  },
  {
    "ContainingType": "WebApplicationtest.Controllers.SanPhamController",
    "Method": "UpdateItem",
    "RelativePath": "api/SanPham/update-item",
    "HttpMethod": "PUT",
    "IsController": true,
    "Order": 0,
    "Parameters": [
      {
        "Name": "model",
        "Type": "Model.SanPhamModel",
        "IsRequired": true
      }
    ],
    "ReturnTypes": [
      {
        "Type": "Model.SanPhamModel",
        "MediaTypes": [
          "text/plain",
          "application/json",
          "text/json"
        ],
        "StatusCode": 200
      }
    ]
  },
  {
    "ContainingType": "WebApplicationtest.Controllers.SoLuongController",
    "Method": "CreateItem",
    "RelativePath": "api/SoLuong/create-item",
    "HttpMethod": "POST",
    "IsController": true,
    "Order": 0,
    "Parameters": [
      {
        "Name": "model",
        "Type": "Model.SoLuongModel",
        "IsRequired": true
      }
    ],
    "ReturnTypes": [
      {
        "Type": "Model.SoLuongModel",
        "MediaTypes": [
          "text/plain",
          "application/json",
          "text/json"
        ],
        "StatusCode": 200
      }
    ]
  },
  {
    "ContainingType": "WebApplicationtest.Controllers.SoLuongController",
    "Method": "DeleteItem",
    "RelativePath": "api/SoLuong/delete-item",
    "HttpMethod": "DELETE",
    "IsController": true,
    "Order": 0,
    "Parameters": [
      {
        "Name": "id",
        "Type": "System.String",
        "IsRequired": true
      }
    ],
    "ReturnTypes": []
  },
  {
    "ContainingType": "WebApplicationtest.Controllers.SoLuongController",
    "Method": "GetAllItem",
    "RelativePath": "api/SoLuong/getall-item",
    "HttpMethod": "GET",
    "IsController": true,
    "Order": 0,
    "Parameters": [],
    "ReturnTypes": [
      {
        "Type": "System.Collections.Generic.IEnumerable\u00601[[Model.SoLuongModel, Model, Version=1.0.0.0, Culture=neutral, PublicKeyToken=null]]",
        "MediaTypes": [
          "text/plain",
          "application/json",
          "text/json"
        ],
        "StatusCode": 200
      }
    ]
  },
  {
    "ContainingType": "WebApplicationtest.Controllers.SoLuongController",
    "Method": "GetAllItembyID",
    "RelativePath": "api/SoLuong/getall-itembyid",
    "HttpMethod": "GET",
    "IsController": true,
    "Order": 0,
    "Parameters": [
      {
        "Name": "id",
        "Type": "System.Int32",
        "IsRequired": false
      }
    ],
    "ReturnTypes": [
      {
        "Type": "System.Collections.Generic.IEnumerable\u00601[[Model.SoLuongModel, Model, Version=1.0.0.0, Culture=neutral, PublicKeyToken=null]]",
        "MediaTypes": [
          "text/plain",
          "application/json",
          "text/json"
        ],
        "StatusCode": 200
      }
    ]
  },
  {
    "ContainingType": "WebApplicationtest.Controllers.SoLuongController",
    "Method": "GetAlltopItem",
    "RelativePath": "api/SoLuong/getalltop-item",
    "HttpMethod": "GET",
    "IsController": true,
    "Order": 0,
    "Parameters": [],
    "ReturnTypes": [
      {
        "Type": "System.Collections.Generic.IEnumerable\u00601[[Model.SoLuongModel, Model, Version=1.0.0.0, Culture=neutral, PublicKeyToken=null]]",
        "MediaTypes": [
          "text/plain",
          "application/json",
          "text/json"
        ],
        "StatusCode": 200
      }
    ]
  },
  {
    "ContainingType": "WebApplicationtest.Controllers.SoLuongController",
    "Method": "UpdateItem",
    "RelativePath": "api/SoLuong/update-item",
    "HttpMethod": "PUT",
    "IsController": true,
    "Order": 0,
    "Parameters": [
      {
        "Name": "model",
        "Type": "Model.SoLuongModel",
        "IsRequired": true
      }
    ],
    "ReturnTypes": [
      {
        "Type": "Model.SoLuongModel",
        "MediaTypes": [
          "text/plain",
          "application/json",
          "text/json"
        ],
        "StatusCode": 200
      }
    ]
  },
  {
    "ContainingType": "WebApplicationtest.Controllers.UsersController",
    "Method": "CreateUser1",
    "RelativePath": "api/Users/create-user1",
    "HttpMethod": "POST",
    "IsController": true,
    "Order": 0,
    "Parameters": [
      {
        "Name": "model",
        "Type": "Model.UserModel",
        "IsRequired": true
      }
    ],
    "ReturnTypes": [
      {
        "Type": "Model.UserModel",
        "MediaTypes": [
          "text/plain",
          "application/json",
          "text/json"
        ],
        "StatusCode": 200
      }
    ]
  },
  {
    "ContainingType": "WebApplicationtest.Controllers.UsersController",
    "Method": "CreateUser2",
    "RelativePath": "api/Users/create-user2",
    "HttpMethod": "POST",
    "IsController": true,
    "Order": 0,
    "Parameters": [
      {
        "Name": "ContentType",
        "Type": "System.String",
        "IsRequired": false
      },
      {
        "Name": "ContentDisposition",
        "Type": "System.String",
        "IsRequired": false
      },
      {
        "Name": "Headers",
        "Type": "Microsoft.AspNetCore.Http.IHeaderDictionary",
        "IsRequired": false
      },
      {
        "Name": "Length",
        "Type": "System.Int64",
        "IsRequired": false
      },
      {
        "Name": "Name",
        "Type": "System.String",
        "IsRequired": false
      },
      {
        "Name": "FileName",
        "Type": "System.String",
        "IsRequired": false
      },
      {
        "Name": "hoten",
        "Type": "System.String",
        "IsRequired": false
      },
      {
        "Name": "ngaysinh",
        "Type": "System.Nullable\u00601[[System.DateTime, System.Private.CoreLib, Version=6.0.0.0, Culture=neutral, PublicKeyToken=7cec85d7bea7798e]]",
        "IsRequired": false
      },
      {
        "Name": "taikhoan",
        "Type": "System.String",
        "IsRequired": false
      },
      {
        "Name": "matkhau",
        "Type": "System.String",
        "IsRequired": false
      }
    ],
    "ReturnTypes": [
      {
        "Type": "Model.UserModel",
        "MediaTypes": [
          "text/plain",
          "application/json",
          "text/json"
        ],
        "StatusCode": 200
      }
    ]
  },
  {
    "ContainingType": "WebApplicationtest.Controllers.UsersController",
    "Method": "DeleteUser",
    "RelativePath": "api/Users/delete-user",
    "HttpMethod": "POST",
    "IsController": true,
    "Order": 0,
    "Parameters": [
      {
        "Name": "formData",
        "Type": "System.Collections.Generic.Dictionary\u00602[[System.String, System.Private.CoreLib, Version=6.0.0.0, Culture=neutral, PublicKeyToken=7cec85d7bea7798e],[System.Object, System.Private.CoreLib, Version=6.0.0.0, Culture=neutral, PublicKeyToken=7cec85d7bea7798e]]",
        "IsRequired": true
      }
    ],
    "ReturnTypes": []
  },
  {
    "ContainingType": "WebApplicationtest.Controllers.UsersController",
    "Method": "DownloadSetupSataProduct",
    "RelativePath": "api/Users/download/{filename}",
    "HttpMethod": "GET",
    "IsController": true,
    "Order": 0,
    "Parameters": [
      {
        "Name": "filename",
        "Type": "System.String",
        "IsRequired": true
      }
    ],
    "ReturnTypes": []
  },
  {
    "ContainingType": "WebApplicationtest.Controllers.UsersController",
    "Method": "GetDatabyID",
    "RelativePath": "api/Users/get-by-id/{id}",
    "HttpMethod": "GET",
    "IsController": true,
    "Order": 0,
    "Parameters": [
      {
        "Name": "id",
        "Type": "System.String",
        "IsRequired": true
      }
    ],
    "ReturnTypes": [
      {
        "Type": "Model.UserModel",
        "MediaTypes": [
          "text/plain",
          "application/json",
          "text/json"
        ],
        "StatusCode": 200
      }
    ]
  },
  {
    "ContainingType": "WebApplicationtest.Controllers.UsersController",
    "Method": "Login",
    "RelativePath": "api/Users/login",
    "HttpMethod": "POST",
    "IsController": true,
    "Order": 0,
    "Parameters": [
      {
        "Name": "model",
        "Type": "Model.AuthenticateModel",
        "IsRequired": true
      }
    ],
    "ReturnTypes": []
  },
  {
    "ContainingType": "WebApplicationtest.Controllers.UsersController",
    "Method": "Search",
    "RelativePath": "api/Users/search",
    "HttpMethod": "POST",
    "IsController": true,
    "Order": 0,
    "Parameters": [
      {
        "Name": "formData",
        "Type": "System.Collections.Generic.Dictionary\u00602[[System.String, System.Private.CoreLib, Version=6.0.0.0, Culture=neutral, PublicKeyToken=7cec85d7bea7798e],[System.Object, System.Private.CoreLib, Version=6.0.0.0, Culture=neutral, PublicKeyToken=7cec85d7bea7798e]]",
        "IsRequired": true
      }
    ],
    "ReturnTypes": [
      {
        "Type": "Model.ResponseModel",
        "MediaTypes": [
          "text/plain",
          "application/json",
          "text/json"
        ],
        "StatusCode": 200
      }
    ]
  },
  {
    "ContainingType": "WebApplicationtest.Controllers.UsersController",
    "Method": "UpdateUser",
    "RelativePath": "api/Users/update-user",
    "HttpMethod": "POST",
    "IsController": true,
    "Order": 0,
    "Parameters": [
      {
        "Name": "model",
        "Type": "Model.UserModel",
        "IsRequired": true
      }
    ],
    "ReturnTypes": [
      {
        "Type": "Model.UserModel",
        "MediaTypes": [
          "text/plain",
          "application/json",
          "text/json"
        ],
        "StatusCode": 200
      }
    ]
  },
  {
    "ContainingType": "WebApplicationtest.Controllers.UsersController",
    "Method": "Upload",
    "RelativePath": "api/Users/upload",
    "HttpMethod": "POST",
    "IsController": true,
    "Order": 0,
    "Parameters": [
      {
        "Name": "file",
        "Type": "Microsoft.AspNetCore.Http.IFormFile",
        "IsRequired": false
      }
    ],
    "ReturnTypes": []
  },
  {
    "ContainingType": "WebApplicationtest.Controllers.WeatherForecastController",
    "Method": "Get",
    "RelativePath": "WeatherForecast",
    "HttpMethod": "GET",
    "IsController": true,
    "Order": 0,
    "Parameters": [],
    "ReturnTypes": [
      {
        "Type": "System.Collections.Generic.IEnumerable\u00601[[WebApplicationtest.WeatherForecast, WebApplicationtest, Version=1.0.0.0, Culture=neutral, PublicKeyToken=null]]",
        "MediaTypes": [
          "text/plain",
          "application/json",
          "text/json"
        ],
        "StatusCode": 200
      }
    ],
    "EndpointName": "GetWeatherForecast"
  }
]